MANIFEST.in
README.rst
setup.py
docs/HISTORY.txt
docs/LICENSE.GPL
docs/LICENSE.txt
ftw/__init__.py
ftw.statusmap.egg-info/PKG-INFO
ftw.statusmap.egg-info/SOURCES.txt
ftw.statusmap.egg-info/dependency_links.txt
ftw.statusmap.egg-info/entry_points.txt
ftw.statusmap.egg-info/namespace_packages.txt
ftw.statusmap.egg-info/not-zip-safe
ftw.statusmap.egg-info/requires.txt
ftw.statusmap.egg-info/top_level.txt
ftw/statusmap/__init__.py
ftw/statusmap/configure.zcml
ftw/statusmap/interfaces.py
ftw/statusmap/testing.py
ftw/statusmap/utils.py
ftw/statusmap/browser/__init__.py
ftw/statusmap/browser/configure.zcml
ftw/statusmap/browser/statusmap.pt
ftw/statusmap/browser/statusmap.py
ftw/statusmap/browser/resource/statusmap.css
ftw/statusmap/browser/resource/statusmap.js
ftw/statusmap/locales/ftw.statusmap.pot
ftw/statusmap/locales/de/LC_MESSAGES/ftw.statusmap.po
ftw/statusmap/profiles/default/actions.xml
ftw/statusmap/profiles/default/metadata.xml
ftw/statusmap/publisher/__init__.py
ftw/statusmap/publisher/checker.py
ftw/statusmap/publisher/configure.zcml
ftw/statusmap/tests/__init__.py
ftw/statusmap/tests/helpers.py
ftw/statusmap/tests/test_ftw_publisher_constraint_checker.py
ftw/statusmap/tests/test_statusmap_integration.py
ftw/statusmap/tests/test_utils.py
ftw/statusmap/tests/test_view.py
ftw/statusmap/tests/test_view_functional.py
ftw/statusmap/upgrades/__init__.py
ftw/statusmap/upgrades/20160224101215_update_action/__init__.py
ftw/statusmap/upgrades/20160224101215_update_action/actions.xml
ftw/statusmap/upgrades/20160224101215_update_action/upgrade.py