Metadata-Version: 1.1
Name: ftw.statusmap
Version: 1.3.0
Summary: A plone view listing objects and review states in a tree.
Home-page: https://github.com/4teamwork/ftw.statusmap
Author: 4teamwork AG
Author-email: mailto:info@4teamwork.ch
License: GPL2
Keywords: ftw statusmap plone workflow tree
Platform: UNKNOWN
Classifier: Programming Language :: Python
Classifier: Framework :: Plone
Classifier: Framework :: Plone :: 4.1
Classifier: Framework :: Plone :: 4.2
Classifier: Framework :: Plone :: 4.3
Classifier: Intended Audience :: Developers
Classifier: Topic :: Software Development :: Libraries :: Python Modules
